maxplotlib/__init__.py
maxplotlib/backends/matplotlib/utils.py
maxplotlib/backends/plotly/__init__.py
maxplotlib/backends/plotly/utils.py
maxplotlib/canvas/__init__.py
maxplotlib/canvas/canvas.py
maxplotlib/colors/__init__.py
maxplotlib/colors/colors.py
maxplotlib/linestyle/__init__.py
maxplotlib/linestyle/linestyle.py
maxplotlib/objects/__init__.py
maxplotlib/objects/node.py
maxplotlib/objects/path.py
maxplotlib/subfigure/__init__.py
maxplotlib/subfigure/line_plot.py
maxplotlib/subfigure/subfigure.py
maxplotlib/tests/test_canvas.py
maxplotlib/tests/test_imports.py
maxplotlib/tests/test_plot.py
maxplotlib/utils/__init__.py
maxplotlib/utils/options.py
maxplotlibx-0.1.3.dist-info/licenses/LICENSE
maxplotlibx-0.1.3.dist-info/METADATA
maxplotlibx-0.1.3.dist-info/WHEEL
maxplotlibx-0.1.3.dist-info/top_level.txt
maxplotlibx-0.1.3.dist-info/RECORD
