Metadata-Version: 2.4
Name: maxplotlibx
Version: 0.1.3
Summary: A reproducible plotting module with various backends and export options.
Author: Max
Project-URL: Source, https://github.com/max-models/maxplotlib
Keywords: matplotlib
Classifier: Development Status :: 3 - Alpha
Requires-Python: >=3.8
License-File: LICENSE
Requires-Dist: matplotlib
Requires-Dist: pint
Requires-Dist: plotly
Requires-Dist: tikzpics>=0.1.1
Provides-Extra: test
Requires-Dist: pytest; extra == "test"
Requires-Dist: coverage; extra == "test"
Provides-Extra: docs
Requires-Dist: myst-parser; extra == "docs"
Requires-Dist: sphinx; extra == "docs"
Requires-Dist: sphinx-rtd-theme; extra == "docs"
Requires-Dist: nbsphinx; extra == "docs"
Requires-Dist: ipykernel; extra == "docs"
Requires-Dist: nbconvert; extra == "docs"
Provides-Extra: dev
Requires-Dist: maxplotlibx[docs,test]; extra == "dev"
Requires-Dist: ruff; extra == "dev"
Requires-Dist: black; extra == "dev"
Requires-Dist: isort; extra == "dev"
Requires-Dist: jupyterlab; extra == "dev"
Requires-Dist: nbstripout; extra == "dev"
Requires-Dist: pre-commit; extra == "dev"
Requires-Dist: pyproject-fmt; extra == "dev"
Dynamic: license-file
